{
	"backtrace" : 1,
	"backtraceGraph" : 
	{
		"commands" : 
		[
			"add_library"
		],
		"files" : 
		[
			"core/CMakeLists.txt"
		],
		"nodes" : 
		[
			{
				"file" : 0
			},
			{
				"command" : 0,
				"file" : 0,
				"line" : 1,
				"parent" : 0
			}
		]
	},
	"id" : "vecpar_core::@57760688d1f824db5d9c",
	"name" : "vecpar_core",
	"paths" : 
	{
		"build" : "core",
		"source" : "core"
	},
	"sourceGroups" : 
	[
		{
			"name" : "Header Files",
			"sourceIndexes" : 
			[
				0,
				1,
				2,
				3,
				4,
				5,
				6,
				7,
				8
			]
		}
	],
	"sources" : 
	[
		{
			"backtrace" : 1,
			"path" : "core/include/vecpar/core/algorithms/detail/map.hpp",
			"sourceGroupIndex" : 0
		},
		{
			"backtrace" : 1,
			"path" : "core/include/vecpar/core/algorithms/detail/filter.hpp",
			"sourceGroupIndex" : 0
		},
		{
			"backtrace" : 1,
			"path" : "core/include/vecpar/core/algorithms/detail/reduce.hpp",
			"sourceGroupIndex" : 0
		},
		{
			"backtrace" : 1,
			"path" : "core/include/vecpar/core/algorithms/parallelizable_map_filter.hpp",
			"sourceGroupIndex" : 0
		},
		{
			"backtrace" : 1,
			"path" : "core/include/vecpar/core/algorithms/parallelizable_map.hpp",
			"sourceGroupIndex" : 0
		},
		{
			"backtrace" : 1,
			"path" : "core/include/vecpar/core/algorithms/parallelizable_reduce.hpp",
			"sourceGroupIndex" : 0
		},
		{
			"backtrace" : 1,
			"path" : "core/include/vecpar/core/algorithms/parallelizable_filter.hpp",
			"sourceGroupIndex" : 0
		},
		{
			"backtrace" : 1,
			"path" : "core/include/vecpar/core/definitions/common.hpp",
			"sourceGroupIndex" : 0
		},
		{
			"backtrace" : 1,
			"path" : "core/include/vecpar/core/definitions/config.hpp",
			"sourceGroupIndex" : 0
		}
	],
	"type" : "INTERFACE_LIBRARY"
}
